paramdb/__init__.py
paramdb/_database.py
paramdb/_param_data/__init__.py
paramdb/_param_data/_collections.py
paramdb/_param_data/_dataclasses.py
paramdb/_param_data/_files.py
paramdb/_param_data/_param_data.py
paramdb/_param_data/_type_mixins.py
paramdb/py.typed
paramdb-0.15.3.dist-info/LICENSE
paramdb-0.15.3.dist-info/METADATA
paramdb-0.15.3.dist-info/WHEEL
paramdb-0.15.3.dist-info/RECORD
