Metadata-Version: 2.3
Name: paramdb
Version: 0.15.3
Summary: Python package for storing and retrieving experiment parameters.
License: BSD-3-Clause
Author: Alex Hadley
Author-email: contact@alexhadley.net
Requires-Python: >=3.9,<4.0
Classifier: License :: OSI Approved :: BSD License
Classifier: Programming Language :: Python :: 3
Classifier: Programming Language :: Python :: 3.9
Classifier: Programming Language :: Python :: 3.10
Classifier: Programming Language :: Python :: 3.11
Classifier: Programming Language :: Python :: 3.12
Classifier: Programming Language :: Python :: 3.13
Provides-Extra: all
Provides-Extra: astropy
Provides-Extra: pandas
Provides-Extra: pydantic
Requires-Dist: astropy (>=6.0.1,<7.0.0) ; extra == "all" or extra == "astropy"
Requires-Dist: eval-type-backport (>=0.2.0,<0.3.0) ; extra == "all" or extra == "pydantic"
Requires-Dist: pandas (>=2.2.2,<3.0.0) ; extra == "all" or extra == "pandas"
Requires-Dist: pydantic (>=2.7.4,<3.0.0) ; extra == "all" or extra == "pydantic"
Requires-Dist: sqlalchemy (>=2.0.31,<3.0.0)
Requires-Dist: typing-extensions (>=4.12.2,<5.0.0)
Requires-Dist: zstandard (>=0.24.0,<0.25.0)
Project-URL: Repository, https://github.com/PainterQubits/paramdb
